.DS_Store
stringlifier/__init__.py
stringlifier/api.py
stringlifier/stringlifier_test.py
stringlifier/data/enhanced-c.bestType
stringlifier/data/enhanced-c.conf
stringlifier/data/enhanced-c.encodings
stringlifier/modules/__init__.py
stringlifier/modules/stringc.py
stringlifier/modules/stringc2.py
stringlifier/modules/training.py
stringlifier39-0.1.1.8.dist-info/LICENSE
stringlifier39-0.1.1.8.dist-info/METADATA
stringlifier39-0.1.1.8.dist-info/WHEEL
stringlifier39-0.1.1.8.dist-info/top_level.txt
stringlifier39-0.1.1.8.dist-info/RECORD
