Metadata-Version: 2.1
Name: stringlifier39
Version: 0.1.1.8
Summary: Python module for detecting password, api keys hashes and any other string that resembles a randomly generated character sequence.
Home-page: https://github.com/adobe/stringlifier
Author: Multiple authors
Author-email: garvit.ism@gmail.com
License: UNKNOWN
Platform: UNKNOWN
Classifier: Programming Language :: Python :: 3.0
Classifier: License :: OSI Approved :: Apache Software License
Classifier: Operating System :: OS Independent
License-File: LICENSE
Requires-Dist: ipdb
Requires-Dist: nptyping (==1.3.0)
Requires-Dist: numpy (==1.22.3)
Requires-Dist: PyJWT
Requires-Dist: torch
Requires-Dist: tqdm
